psyscale/__init__.py
psyscale/async_core.py
psyscale/core.py
psyscale/dev.py
psyscale/metadata_partial.py
psyscale/series_data_partial.py
psyscale/series_df.py
psyscale/symbols_partial.py
psyscale/timescale.yml
psyscale/timeseries_partial.py
psyscale/psql/__init__.py
psyscale/psql/commands_obj.py
psyscale/psql/enum.py
psyscale/psql/generic.py
psyscale/psql/orm.py
psyscale/psql/security.py
psyscale/psql/timeseries.py
psyscale-0.1.2.dist-info/licenses/LICENSE
psyscale-0.1.2.dist-info/METADATA
psyscale-0.1.2.dist-info/WHEEL
psyscale-0.1.2.dist-info/top_level.txt
psyscale-0.1.2.dist-info/RECORD
