Metadata-Version: 2.4
Name: psyscale
Version: 0.1.2
Summary: A Python library for storing & retrieving financial data in a TimescaleDB optimized Postgres Database.
Author-email: Bryce Hawk <bryce.m.hawk@gmail.com>
License-Expression: MIT
Keywords: Docker,pandas,pandas_market_calendars,psycopg,PostgreSQL,TimescaleDB
Classifier: Operating System :: OS Independent
Classifier: Development Status :: 4 - Beta
Classifier: Framework :: AsyncIO
Classifier: Programming Language :: Python
Classifier: Programming Language :: Python :: 3
Requires-Python: >=3.12
License-File: LICENSE
Requires-Dist: pandas>=2.2.2
Requires-Dist: python-dotenv>=1.1.0
Requires-Dist: pandas-market-calendars>=5.0.0
Requires-Dist: psycopg[binary,pool]>=3.2.6
Provides-Extra: dev
Requires-Dist: alpaca-py>=0.39.4; extra == "dev"
Provides-Extra: test
Requires-Dist: pytest>=8.3.5; extra == "test"
Requires-Dist: pytest-asyncio>=0.26.0; extra == "test"
Requires-Dist: testcontainers>=4.10.0; extra == "test"
Requires-Dist: coverage>=7.8.0; extra == "test"
Provides-Extra: dist
Requires-Dist: setuptools>=80.7.1; extra == "dist"
Requires-Dist: twine>=6.1.0; extra == "dist"
Requires-Dist: wheel>=0.45.1; extra == "dist"
Requires-Dist: build>=1.2.2.post1; extra == "dist"
Dynamic: license-file
